apsimNGpy/.DS_Store
apsimNGpy/.env
apsimNGpy/CITATION.cff
apsimNGpy/README.RST
apsimNGpy/__init__.py
apsimNGpy/config.py
apsimNGpy/exceptions.py
apsimNGpy/release.py
apsimNGpy/requirements.txt
apsimNGpy/settings.py
apsimNGpy/version.py
apsimNGpy/.idea/.name
apsimNGpy/.idea/apsimNGpy.iml
apsimNGpy/.idea/misc.xml
apsimNGpy/.idea/modules.xml
apsimNGpy/.idea/vcs.xml
apsimNGpy/.idea/workspace.xml
apsimNGpy/.idea/inspectionProfiles/Project_Default.xml
apsimNGpy/.idea/inspectionProfiles/profiles_settings.xml
apsimNGpy/.idea/shelf/Uncommitted_changes_before_Update_at_10_27_2024_12_50_AM__Changes_.xml
apsimNGpy/.idea/shelf/Uncommitted_changes_before_Update_at_10_27_2024_12_50_AM_[Changes]/shelved.patch
apsimNGpy/__pycache__/__init__.cpython-311.pyc
apsimNGpy/__pycache__/__init__.cpython-312.pyc
apsimNGpy/__pycache__/exceptions.cpython-312.pyc
apsimNGpy/__pycache__/settings.cpython-312.pyc
apsimNGpy/__pycache__/version.cpython-312.pyc
apsimNGpy/bin_loader/README
apsimNGpy/bin_loader/__file__.py
apsimNGpy/bin_loader/configs.ini
apsimNGpy/bin_loader/resources.py
apsimNGpy/bin_loader/__pycache__/resources.cpython-312.pyc
apsimNGpy/build_from_source/install_apsimx.log
apsimNGpy/build_from_source/windows.bat
apsimNGpy/cli/__init__.py
apsimNGpy/cli/_args.py
apsimNGpy/cli/apsim.py
apsimNGpy/cli/cli.py
apsimNGpy/cli/cli.rst
apsimNGpy/cli/client.py
apsimNGpy/cli/commands.py
apsimNGpy/cli/configs.ini
apsimNGpy/cli/fast_api.py
apsimNGpy/cli/model_desc.py
apsimNGpy/cli/req.py
apsimNGpy/cli/server.py
apsimNGpy/cli/set_bin.py
apsimNGpy/cli/set_ups.py
apsimNGpy/cli/__pycache__/__init__.cpython-312.pyc
apsimNGpy/cli/__pycache__/set_ups.cpython-312.pyc
apsimNGpy/config/6r.py
apsimNGpy/config/README.rst
apsimNGpy/config/__init__.py
apsimNGpy/config/apsim_versions.py
apsimNGpy/config/bin_config.py
apsimNGpy/config/config.py
apsimNGpy/config/configs.ini
apsimNGpy/core/._db
apsimNGpy/core/README.rst
apsimNGpy/core/__core_table___e2c0dd0735864f5695c3a8d4be4f4d4d_7744
apsimNGpy/core/__init__.py
apsimngpy-1.2.2.dist-info/LICENSE
apsimngpy-1.2.2.dist-info/METADATA
apsimngpy-1.2.2.dist-info/WHEEL
apsimngpy-1.2.2.dist-info/entry_points.txt
apsimngpy-1.2.2.dist-info/top_level.txt
apsimngpy-1.2.2.dist-info/RECORD
