Metadata-Version: 2.1
Name: apsimngpy
Version: 1.2.2
Summary: APSIM next generation package interface
Home-page: https://github.com/MAGALA-RICHARD/apsimNGpy.git
Author: Richard Magala
Author-email: Richard Magala <magalarich20@gmail.com>
License: Apache License
Project-URL: Homepage, https://github.com/MAGALA-RICHARD/apsimNGpy.git
Keywords: python,APSIM Next Generation,pythonnet,crop modeling
Classifier: License :: OSI Approved :: Apache Software License
Classifier: Development Status :: 3 - Alpha
Classifier: Intended Audience :: Science/Research
Classifier: Intended Audience :: Education
Classifier: Topic :: Scientific/Engineering :: Visualization
Classifier: Topic :: Scientific/Engineering :: Information Analysis
Classifier: Programming Language :: Python :: 3
Classifier: Programming Language :: Python :: 3.10
Classifier: Operating System :: OS Independent
Requires-Python: >=3.10,<3.14
License-File: ./LICENSE
Requires-Dist: numpy>=1.20.0
Requires-Dist: scipy>=1.7
Requires-Dist: xmltodict>=0.13.0
Requires-Dist: requests>=2.31.0
Requires-Dist: pythonnet>=3.0.1
Requires-Dist: rasterio>=1.3.8
Requires-Dist: shapely>=2.0.1
Requires-Dist: clr>=1.0.3
Requires-Dist: geopandas>=0.13.2
Requires-Dist: seaborn>=0.13.2
Requires-Dist: pandas>=2.0.3
Requires-Dist: geopy>=2.4.1
Requires-Dist: joblib>=1.3.2
Requires-Dist: sqlalchemy>=2.0
Requires-Dist: matplotlib
Requires-Dist: psutil>=6.0.0
Requires-Dist: tenacity
Requires-Dist: typer
Requires-Dist: pymoo
Requires-Dist: tqdm==4.67.1
Requires-Dist: wrapdisc==2.5.0
Requires-Dist: SALib==1.5.2
Requires-Dist: python-dotenv<2.0.0,>=1.0.1
Requires-Dist: summarytools>=0.3.0
Requires-Dist: watchdog==6.0.0
Requires-Dist: loguru==0.7.3
